{"match_number": "3651102", "home_team": {"name": "RasenBallsport Leipzig", "number": "23826", "starting_lineup": [{"name": "Gul\u00e1csi", "profile_link": "/peter-gulacsi/profil/spieler/57071", "top": "80%", "left": "40%", "nationality": "Ungarn"}, {"name": "Gvardiol", "profile_link": "/josko-gvardiol/profil/spieler/475959", "top": "62%", "left": "40%", "nationality": "Kroatien"}, {"name": "Simakan", "profile_link": "/mohamed-simakan/profil/spieler/666234", "top": "61%", "left": "15%", "nationality": "Frankreich"}, {"name": "Orb\u00e1n", "profile_link": "/willi-orban/profil/spieler/93740", "top": "61%", "left": "65%", "nationality": "Ungarn"}, {"name": "Angeli\u00f1o", "profile_link": "/angelino/profil/spieler/277179", "top": "32%", "left": "12%", "nationality": "Spanien"}, {"name": "Mukiele", "profile_link": "/nordi-mukiele/profil/spieler/348026", "top": "32%", "left": "68%", "nationality": "Frankreich"}, {"name": "Adams", "profile_link": "/tyler-adams/profil/spieler/332705", "top": "35%", "left": "30%", "nationality": "Vereinigte Staaten"}, {"name": "Laimer", "profile_link": "/konrad-laimer/profil/spieler/223967", "top": "35%", "left": "50%", "nationality": "\u00d6sterreich"}, {"name": "Forsberg", "profile_link": "/emil-forsberg/profil/spieler/111078", "top": "10%", "left": "15%", "nationality": "Schweden"}, {"name": "Nkunku", "profile_link": "/christopher-nkunku/profil/spieler/344381", "top": "10%", "left": "65%", "nationality": "Frankreich"}, {"name": "Silva", "profile_link": "/andre-silva/profil/spieler/198008", "top": "3%", "left": "40%", "nationality": "Portugal"}]}, "away_team": {"name": "FC Paris Saint-Germain", "number": "583", "starting_lineup": [{"name": "Donnarumma", "profile_link": "/gianluigi-donnarumma/profil/spieler/315858", "top": "80%", "left": "40%", "nationality": "Italien"}, {"name": "Kimpembe", "profile_link": "/presnel-kimpembe/profil/spieler/282041", "top": "63%", "left": "28%", "nationality": "Frankreich"}, {"name": "Marquinhos", "profile_link": "/marquinhos/profil/spieler/181767", "top": "63%", "left": "52.5%", "nationality": "Brasilien"}, {"name": "Mendes", "profile_link": "/nuno-mendes/profil/spieler/616341", "top": "61%", "left": "7.5%", "nationality": "Portugal"}, {"name": "Hakimi", "profile_link": "/achraf-hakimi/profil/spieler/398073", "top": "61%", "left": "73%", "nationality": "Marokko"}, {"name": "Pereira", "profile_link": "/danilo-pereira/profil/spieler/141050", "top": "39%", "left": "40%", "nationality": "Portugal"}, {"name": "Gueye", "profile_link": "/idrissa-gueye/profil/spieler/126665", "top": "28%", "left": "53%", "nationality": "Senegal"}, {"name": "Wijnaldum", "profile_link": "/georginio-wijnaldum/profil/spieler/49499", "top": "28%", "left": "27%", "nationality": "Niederlande"}, {"name": "Neymar", "profile_link": "/neymar/profil/spieler/68290", "top": "10%", "left": "15%", "nationality": "Brasilien"}, {"name": "Di Mar\u00eda", "profile_link": "/angel-di-maria/profil/spieler/45320", "top": "10%", "left": "65%", "nationality": "Argentinien"}, {"name": "Mbapp\u00e9", "profile_link": "/kylian-mbappe/profil/spieler/342229", "top": "3%", "left": "40%", "nationality": "Frankreich"}]}, "competition_stage": "GROUP_STAGE", "match_result": {"goals_home_team": "2", "goals_away_team": "2"}}